matrice_instance_manager/__init__.py
matrice_instance_manager/__init__.pyi
matrice_instance_manager/action_instance.cpython-312-x86_64-linux-gnu.so
matrice_instance_manager/action_instance.pyi
matrice_instance_manager/actions_manager.cpython-312-x86_64-linux-gnu.so
matrice_instance_manager/actions_manager.pyi
matrice_instance_manager/actions_scaledown_manager.cpython-312-x86_64-linux-gnu.so
matrice_instance_manager/actions_scaledown_manager.pyi
matrice_instance_manager/instance_manager.cpython-312-x86_64-linux-gnu.so
matrice_instance_manager/instance_manager.pyi
matrice_instance_manager/instance_utils.cpython-312-x86_64-linux-gnu.so
matrice_instance_manager/instance_utils.pyi
matrice_instance_manager/prechecks.cpython-312-x86_64-linux-gnu.so
matrice_instance_manager/prechecks.pyi
matrice_instance_manager/py.typed
matrice_instance_manager/resources_tracker.cpython-312-x86_64-linux-gnu.so
matrice_instance_manager/resources_tracker.pyi
matrice_instance_manager/scaling.cpython-312-x86_64-linux-gnu.so
matrice_instance_manager/scaling.pyi
matrice_instance_manager/shutdown_manager.cpython-312-x86_64-linux-gnu.so
matrice_instance_manager/shutdown_manager.pyi
matrice_instance_manager/task_utils.cpython-312-x86_64-linux-gnu.so
matrice_instance_manager/task_utils.pyi
matrice_instance_manager-0.0.1.dist-info/licenses/LICENSE.txt
matrice_instance_manager-0.0.1.dist-info/METADATA
matrice_instance_manager-0.0.1.dist-info/WHEEL
matrice_instance_manager-0.0.1.dist-info/top_level.txt
matrice_instance_manager-0.0.1.dist-info/RECORD
