Metadata-Version: 2.4
Name: matrice_instance_manager
Version: 0.0.1
Summary: Instance management utilities for Matrice.ai services
Author-email: "Matrice.ai" <dipendra@matrice.ai>
License-Expression: MIT
Keywords: matrice,instance,management,utilities,cython
Classifier: Development Status :: 4 - Beta
Classifier: Intended Audience :: Developers
Classifier: Operating System :: POSIX :: Linux
Classifier: Topic :: Software Development :: Libraries :: Python Modules
Classifier: Programming Language :: Python :: 3
Classifier: Programming Language :: Python :: 3.7
Classifier: Programming Language :: Python :: 3.8
Classifier: Programming Language :: Python :: 3.9
Classifier: Programming Language :: Python :: 3.10
Classifier: Programming Language :: Python :: 3.11
Classifier: Programming Language :: Python :: 3.12
Classifier: Typing :: Typed
Requires-Python: <4,>=3.7
License-File: LICENSE.txt
Dynamic: license-file
